xolobbbccc/__init__.py
xolobbbccc-1.0.dist-info/METADATA
xolobbbccc-1.0.dist-info/WHEEL
xolobbbccc-1.0.dist-info/top_level.txt
xolobbbccc-1.0.dist-info/RECORD
