Metadata-Version: 2.1
Name: xolobbbccc
Version: 1.0
Requires-Dist: requests
